nloed/__init__.py
nloed/design.py
nloed/model.py
nloed-0.0.2.dist-info/LICENSE
nloed-0.0.2.dist-info/METADATA
nloed-0.0.2.dist-info/WHEEL
nloed-0.0.2.dist-info/top_level.txt
nloed-0.0.2.dist-info/RECORD
