Metadata-Version: 2.1
Name: nloed
Version: 0.0.2
Summary: A package for nonlinear optimal experimental design
Home-page: https://github.com/NateBraniff/NLoed
Author: Nate Braniff
Author-email: nbraniff@uwaterloo.ca
License: LGPLv3+
Keywords: Optimal,Experimental,Design
Platform: UNKNOWN
Classifier: Programming Language :: Python :: 3
Classifier: Operating System :: OS Independent
Requires-Python: >=3.6.1
Requires-Dist: casadi (>=3.5.0)
Requires-Dist: numpy (>=1.17.0)
Requires-Dist: pandas (>=1.0.0)
Requires-Dist: scipy
Requires-Dist: matplotlib
